[
    {
        "id": 1,
        "name": "Insertion Sort",
        "url": "https://neetcode.io/problems/insertionSort",
        "difficulty": "easy",
        "last_reviewed": null,
        "sr_score": 0,
        "attempted": false
    },
    {
        "id": 2,
        "name": "Merge Sort",
        "url": "https://neetcode.io/problems/mergeSort",
        "difficulty": "medium",
        "last_reviewed": null,
        "sr_score": 0,
        "attempted": false
    },
    {
        "id": 3,
        "name": "Quick Sort",
        "url": "https://neetcode.io/problems/quickSort",
        "difficulty": "medium",
        "last_reviewed": null,
        "sr_score": 0,
        "attempted": false
    },
    {
        "id": 4,
        "name": "Matrix Depth-First Search",
        "url": "https://neetcode.io/problems/matrixDFS",
        "difficulty": "medium",
        "last_reviewed": null,
        "sr_score": 0,
        "attempted": false
    },
    {
        "id": 5,
        "name": "Matrix Breadth-First Search",
        "url": "https://neetcode.io/problems/matrixBFS",
        "difficulty": "medium",
        "last_reviewed": null,
        "sr_score": 0,
        "attempted": false
    },
    {
        "id": 6,
        "name": "Dijkstra's Algorithm",
        "url": "https://neetcode.io/problems/dijkstra",
        "difficulty": "medium",
        "last_reviewed": null,
        "sr_score": 0,
        "attempted": false
    },
    {
        "id": 7,
        "name": "Prim's Algorithm",
        "url": "https://neetcode.io/problems/prim",
        "difficulty": "hard",
        "last_reviewed": null,
        "sr_score": 0,
        "attempted": false
    },
    {
        "id": 8,
        "name": "Kruskal's Algorithm",
        "url": "https://neetcode.io/problems/kruskal",
        "difficulty": "hard",
        "last_reviewed": null,
        "sr_score": 0,
        "attempted": false
    },
    {
        "id": 9,
        "name": "Topological Sort",
        "url": "https://neetcode.io/problems/topologicalSort",
        "difficulty": "hard",
        "last_reviewed": null,
        "sr_score": 0,
        "attempted": false
    },
    {
        "id": 10,
        "name": "0 / 1 Knapsack",
        "url": "https://neetcode.io/problems/zeroOneKnapsack",
        "difficulty": "medium",
        "last_reviewed": null,
        "sr_score": 0,
        "attempted": false
    },
    {
        "id": 11,
        "name": "Unbounded Knapsack",
        "url": "https://neetcode.io/problems/unboundedKnapsack",
        "difficulty": "medium",
        "last_reviewed": null,
        "sr_score": 0,
        "attempted": false
    },
    {
        "id": 12,
        "name": "Contains Duplicate",
        "url": "https://neetcode.io/problems/duplicate-integer",
        "difficulty": "easy",
        "last_reviewed": null,
        "sr_score": 0,
        "attempted": false
    },
    {
        "id": 13,
        "name": "Two Sum",
        "url": "https://neetcode.io/problems/two-integer-sum",
        "difficulty": "easy",
        "last_reviewed": null,
        "sr_score": 0,
        "attempted": false
    },
    {
        "id": 14,
        "name": "Encode and Decode Strings",
        "url": "https://neetcode.io/problems/string-encode-and-decode",
        "difficulty": "medium",
        "last_reviewed": null,
        "sr_score": 0,
        "attempted": false
    },
    {
        "id": 15,
        "name": "Number of Connected Components in an Undirected Graph",
        "url": "https://neetcode.io/problems/count-connected-components",
        "difficulty": "medium",
        "last_reviewed": null,
        "sr_score": 0,
        "attempted": false
    },
    {
        "id": 16,
        "name": "Graph Valid Tree",
        "url": "https://neetcode.io/problems/valid-tree",
        "difficulty": "medium",
        "last_reviewed": null,
        "sr_score": 0,
        "attempted": false
    },
    {
        "id": 17,
        "name": "Alien Dictionary",
        "url": "https://neetcode.io/problems/foreign-dictionary",
        "difficulty": "hard",
        "last_reviewed": null,
        "sr_score": 0,
        "attempted": false
    },
    {
        "id": 18,
        "name": "Meeting Rooms",
        "url": "https://neetcode.io/problems/meeting-schedule",
        "difficulty": "easy",
        "last_reviewed": null,
        "sr_score": 0,
        "attempted": false
    },
    {
        "id": 19,
        "name": "Meeting Rooms II",
        "url": "https://neetcode.io/problems/meeting-schedule-ii",
        "difficulty": "medium",
        "last_reviewed": null,
        "sr_score": 0,
        "attempted": false
    },
    {
        "id": 20,
        "name": "Valid Anagram",
        "url": "https://neetcode.io/problems/is-anagram",
        "difficulty": "easy",
        "last_reviewed": null,
        "sr_score": 0,
        "attempted": false
    },
    {
        "id": 21,
        "name": "Valid Palindrome",
        "url": "https://neetcode.io/problems/is-palindrome",
        "difficulty": "easy",
        "last_reviewed": null,
        "sr_score": 0,
        "attempted": false
    },
    {
        "id": 22,
        "name": "Islands and Treasure",
        "url": "https://neetcode.io/problems/islands-and-treasure",
        "difficulty": "medium",
        "last_reviewed": null,
        "sr_score": 0,
        "attempted": false
    },
    {
        "id": 23,
        "name": "Best Time to Buy and Sell Stock",
        "url": "https://neetcode.io/problems/buy-and-sell-crypto",
        "difficulty": "easy",
        "last_reviewed": null,
        "sr_score": 0,
        "attempted": false
    },
    {
        "id": 24,
        "name": "Valid Parentheses",
        "url": "https://neetcode.io/problems/validate-parentheses",
        "difficulty": "easy",
        "last_reviewed": null,
        "sr_score": 0,
        "attempted": false
    },
    {
        "id": 25,
        "name": "Find Minimum in Rotated Sorted Array",
        "url": "https://neetcode.io/problems/find-minimum-in-rotated-sorted-array",
        "difficulty": "medium",
        "last_reviewed": null,
        "sr_score": 0,
        "attempted": false
    },
    {
        "id": 26,
        "name": "Reverse Linked List",
        "url": "https://neetcode.io/problems/reverse-a-linked-list",
        "difficulty": "easy",
        "last_reviewed": null,
        "sr_score": 0,
        "attempted": false
    },
    {
        "id": 27,
        "name": "Invert Binary Tree",
        "url": "https://neetcode.io/problems/invert-a-binary-tree",
        "difficulty": "easy",
        "last_reviewed": null,
        "sr_score": 0,
        "attempted": false
    },
    {
        "id": 28,
        "name": "Implement Trie (Prefix Tree)",
        "url": "https://neetcode.io/problems/implement-prefix-tree",
        "difficulty": "medium",
        "last_reviewed": null,
        "sr_score": 0,
        "attempted": false
    },
    {
        "id": 29,
        "name": "Find Median From Data Stream",
        "url": "https://neetcode.io/problems/find-median-in-a-data-stream",
        "difficulty": "hard",
        "last_reviewed": null,
        "sr_score": 0,
        "attempted": false
    },
    {
        "id": 30,
        "name": "Combination Sum",
        "url": "https://neetcode.io/problems/combination-target-sum",
        "difficulty": "medium",
        "last_reviewed": null,
        "sr_score": 0,
        "attempted": false
    },
    {
        "id": 31,
        "name": "Number of Islands",
        "url": "https://neetcode.io/problems/count-number-of-islands",
        "difficulty": "medium",
        "last_reviewed": null,
        "sr_score": 0,
        "attempted": false
    },
    {
        "id": 32,
        "name": "Climbing Stairs",
        "url": "https://neetcode.io/problems/climbing-stairs",
        "difficulty": "easy",
        "last_reviewed": null,
        "sr_score": 0,
        "attempted": false
    },
    {
        "id": 33,
        "name": "Unique Paths",
        "url": "https://neetcode.io/problems/count-paths",
        "difficulty": "medium",
        "last_reviewed": null,
        "sr_score": 0,
        "attempted": false
    },
    {
        "id": 34,
        "name": "Maximum Subarray",
        "url": "https://neetcode.io/problems/maximum-subarray",
        "difficulty": "medium",
        "last_reviewed": null,
        "sr_score": 0,
        "attempted": false
    },
    {
        "id": 35,
        "name": "Insert Interval",
        "url": "https://neetcode.io/problems/insert-new-interval",
        "difficulty": "medium",
        "last_reviewed": null,
        "sr_score": 0,
        "attempted": false
    },
    {
        "id": 36,
        "name": "Rotate Image",
        "url": "https://neetcode.io/problems/rotate-matrix",
        "difficulty": "medium",
        "last_reviewed": null,
        "sr_score": 0,
        "attempted": false
    },
    {
        "id": 37,
        "name": "Number of One Bits",
        "url": "https://neetcode.io/problems/number-of-one-bits",
        "difficulty": "easy",
        "last_reviewed": null,
        "sr_score": 0,
        "attempted": false
    },
    {
        "id": 38,
        "name": "Products of Array Except Self",
        "url": "https://neetcode.io/problems/products-of-array-discluding-self",
        "difficulty": "medium",
        "last_reviewed": null,
        "sr_score": 0,
        "attempted": false
    },
    {
        "id": 39,
        "name": "Longest Consecutive Sequence",
        "url": "https://neetcode.io/problems/longest-consecutive-sequence",
        "difficulty": "medium",
        "last_reviewed": null,
        "sr_score": 0,
        "attempted": false
    },
    {
        "id": 40,
        "name": "3Sum",
        "url": "https://neetcode.io/problems/three-integer-sum",
        "difficulty": "medium",
        "last_reviewed": null,
        "sr_score": 0,
        "attempted": false
    },
    {
        "id": 41,
        "name": "Container With Most Water",
        "url": "https://neetcode.io/problems/max-water-container",
        "difficulty": "medium",
        "last_reviewed": null,
        "sr_score": 0,
        "attempted": false
    },
    {
        "id": 42,
        "name": "Longest Substring Without Repeating Characters",
        "url": "https://neetcode.io/problems/longest-substring-without-duplicates",
        "difficulty": "medium",
        "last_reviewed": null,
        "sr_score": 0,
        "attempted": false
    },
    {
        "id": 43,
        "name": "Longest Repeating Character Replacement",
        "url": "https://neetcode.io/problems/longest-repeating-substring-with-replacement",
        "difficulty": "medium",
        "last_reviewed": null,
        "sr_score": 0,
        "attempted": false
    },
    {
        "id": 44,
        "name": "Minimum Window Substring",
        "url": "https://neetcode.io/problems/minimum-window-with-characters",
        "difficulty": "hard",
        "last_reviewed": null,
        "sr_score": 0,
        "attempted": false
    },
    {
        "id": 45,
        "name": "Search in Rotated Sorted Array",
        "url": "https://neetcode.io/problems/find-target-in-rotated-sorted-array",
        "difficulty": "medium",
        "last_reviewed": null,
        "sr_score": 0,
        "attempted": false
    },
    {
        "id": 46,
        "name": "Merge Two Sorted Linked Lists",
        "url": "https://neetcode.io/problems/merge-two-sorted-linked-lists",
        "difficulty": "easy",
        "last_reviewed": null,
        "sr_score": 0,
        "attempted": false
    },
    {
        "id": 47,
        "name": "Reorder Linked List",
        "url": "https://neetcode.io/problems/reorder-linked-list",
        "difficulty": "medium",
        "last_reviewed": null,
        "sr_score": 0,
        "attempted": false
    },
    {
        "id": 48,
        "name": "Remove Node From End of Linked List",
        "url": "https://neetcode.io/problems/remove-node-from-end-of-linked-list",
        "difficulty": "medium",
        "last_reviewed": null,
        "sr_score": 0,
        "attempted": false
    },
    {
        "id": 49,
        "name": "Linked List Cycle Detection",
        "url": "https://neetcode.io/problems/linked-list-cycle-detection",
        "difficulty": "easy",
        "last_reviewed": null,
        "sr_score": 0,
        "attempted": false
    },
    {
        "id": 50,
        "name": "Merge K Sorted Linked Lists",
        "url": "https://neetcode.io/problems/merge-k-sorted-linked-lists",
        "difficulty": "hard",
        "last_reviewed": null,
        "sr_score": 0,
        "attempted": false
    },
    {
        "id": 51,
        "name": "Maximum Depth of Binary Tree",
        "url": "https://neetcode.io/problems/depth-of-binary-tree",
        "difficulty": "easy",
        "last_reviewed": null,
        "sr_score": 0,
        "attempted": false
    },
    {
        "id": 52,
        "name": "Same Binary Tree",
        "url": "https://neetcode.io/problems/same-binary-tree",
        "difficulty": "easy",
        "last_reviewed": null,
        "sr_score": 0,
        "attempted": false
    },
    {
        "id": 53,
        "name": "Subtree of Another Tree",
        "url": "https://neetcode.io/problems/subtree-of-a-binary-tree",
        "difficulty": "easy",
        "last_reviewed": null,
        "sr_score": 0,
        "attempted": false
    },
    {
        "id": 54,
        "name": "Design Add and Search Word Data Structure",
        "url": "https://neetcode.io/problems/design-word-search-data-structure",
        "difficulty": "medium",
        "last_reviewed": null,
        "sr_score": 0,
        "attempted": false
    },
    {
        "id": 55,
        "name": "Word Search",
        "url": "https://neetcode.io/problems/search-for-word",
        "difficulty": "medium",
        "last_reviewed": null,
        "sr_score": 0,
        "attempted": false
    },
    {
        "id": 56,
        "name": "Word Search II",
        "url": "https://neetcode.io/problems/search-for-word-ii",
        "difficulty": "hard",
        "last_reviewed": null,
        "sr_score": 0,
        "attempted": false
    },
    {
        "id": 57,
        "name": "Clone Graph",
        "url": "https://neetcode.io/problems/clone-graph",
        "difficulty": "medium",
        "last_reviewed": null,
        "sr_score": 0,
        "attempted": false
    },
    {
        "id": 58,
        "name": "Pacific Atlantic Water Flow",
        "url": "https://neetcode.io/problems/pacific-atlantic-water-flow",
        "difficulty": "medium",
        "last_reviewed": null,
        "sr_score": 0,
        "attempted": false
    },
    {
        "id": 59,
        "name": "Course Schedule",
        "url": "https://neetcode.io/problems/course-schedule",
        "difficulty": "medium",
        "last_reviewed": null,
        "sr_score": 0,
        "attempted": false
    },
    {
        "id": 60,
        "name": "House Robber",
        "url": "https://neetcode.io/problems/house-robber",
        "difficulty": "medium",
        "last_reviewed": null,
        "sr_score": 0,
        "attempted": false
    },
    {
        "id": 61,
        "name": "House Robber II",
        "url": "https://neetcode.io/problems/house-robber-ii",
        "difficulty": "medium",
        "last_reviewed": null,
        "sr_score": 0,
        "attempted": false
    },
    {
        "id": 62,
        "name": "Longest Palindromic Substring",
        "url": "https://neetcode.io/problems/longest-palindromic-substring",
        "difficulty": "medium",
        "last_reviewed": null,
        "sr_score": 0,
        "attempted": false
    },
    {
        "id": 63,
        "name": "Palindromic Substrings",
        "url": "https://neetcode.io/problems/palindromic-substrings",
        "difficulty": "medium",
        "last_reviewed": null,
        "sr_score": 0,
        "attempted": false
    },
    {
        "id": 64,
        "name": "Decode Ways",
        "url": "https://neetcode.io/problems/decode-ways",
        "difficulty": "medium",
        "last_reviewed": null,
        "sr_score": 0,
        "attempted": false
    },
    {
        "id": 65,
        "name": "Coin Change",
        "url": "https://neetcode.io/problems/coin-change",
        "difficulty": "medium",
        "last_reviewed": null,
        "sr_score": 0,
        "attempted": false
    },
    {
        "id": 66,
        "name": "Maximum Product Subarray",
        "url": "https://neetcode.io/problems/maximum-product-subarray",
        "difficulty": "medium",
        "last_reviewed": null,
        "sr_score": 0,
        "attempted": false
    },
    {
        "id": 67,
        "name": "Word Break",
        "url": "https://neetcode.io/problems/word-break",
        "difficulty": "medium",
        "last_reviewed": null,
        "sr_score": 0,
        "attempted": false
    },
    {
        "id": 68,
        "name": "Longest Increasing Subsequence",
        "url": "https://neetcode.io/problems/longest-increasing-subsequence",
        "difficulty": "medium",
        "last_reviewed": null,
        "sr_score": 0,
        "attempted": false
    },
    {
        "id": 69,
        "name": "Longest Common Subsequence",
        "url": "https://neetcode.io/problems/longest-common-subsequence",
        "difficulty": "medium",
        "last_reviewed": null,
        "sr_score": 0,
        "attempted": false
    },
    {
        "id": 70,
        "name": "Jump Game",
        "url": "https://neetcode.io/problems/jump-game",
        "difficulty": "medium",
        "last_reviewed": null,
        "sr_score": 0,
        "attempted": false
    },
    {
        "id": 71,
        "name": "Merge Intervals",
        "url": "https://neetcode.io/problems/merge-intervals",
        "difficulty": "medium",
        "last_reviewed": null,
        "sr_score": 0,
        "attempted": false
    },
    {
        "id": 72,
        "name": "Non-overlapping Intervals",
        "url": "https://neetcode.io/problems/non-overlapping-intervals",
        "difficulty": "medium",
        "last_reviewed": null,
        "sr_score": 0,
        "attempted": false
    },
    {
        "id": 73,
        "name": "Spiral Matrix",
        "url": "https://neetcode.io/problems/spiral-matrix",
        "difficulty": "medium",
        "last_reviewed": null,
        "sr_score": 0,
        "attempted": false
    },
    {
        "id": 74,
        "name": "Set Matrix Zeroes",
        "url": "https://neetcode.io/problems/set-zeroes-in-matrix",
        "difficulty": "medium",
        "last_reviewed": null,
        "sr_score": 0,
        "attempted": false
    },
    {
        "id": 75,
        "name": "Counting Bits",
        "url": "https://neetcode.io/problems/counting-bits",
        "difficulty": "easy",
        "last_reviewed": null,
        "sr_score": 0,
        "attempted": false
    },
    {
        "id": 76,
        "name": "Reverse Bits",
        "url": "https://neetcode.io/problems/reverse-bits",
        "difficulty": "easy",
        "last_reviewed": null,
        "sr_score": 0,
        "attempted": false
    },
    {
        "id": 77,
        "name": "Missing Number",
        "url": "https://neetcode.io/problems/missing-number",
        "difficulty": "easy",
        "last_reviewed": null,
        "sr_score": 0,
        "attempted": false
    },
    {
        "id": 78,
        "name": "Sum of Two Integers",
        "url": "https://neetcode.io/problems/sum-of-two-integers",
        "difficulty": "medium",
        "last_reviewed": null,
        "sr_score": 0,
        "attempted": false
    },
    {
        "id": 79,
        "name": "Top K Frequent Elements",
        "url": "https://neetcode.io/problems/top-k-elements-in-list",
        "difficulty": "medium",
        "last_reviewed": null,
        "sr_score": 0,
        "attempted": false
    },
    {
        "id": 80,
        "name": "Group Anagrams",
        "url": "https://neetcode.io/problems/anagram-groups",
        "difficulty": "medium",
        "last_reviewed": null,
        "sr_score": 0,
        "attempted": false
    },
    {
        "id": 81,
        "name": "Lowest Common Ancestor in Binary Search Tree",
        "url": "https://neetcode.io/problems/lowest-common-ancestor-in-binary-search-tree",
        "difficulty": "medium",
        "last_reviewed": null,
        "sr_score": 0,
        "attempted": false
    },
    {
        "id": 82,
        "name": "Binary Tree Level Order Traversal",
        "url": "https://neetcode.io/problems/level-order-traversal-of-binary-tree",
        "difficulty": "medium",
        "last_reviewed": null,
        "sr_score": 0,
        "attempted": false
    },
    {
        "id": 83,
        "name": "Valid Binary Search Tree",
        "url": "https://neetcode.io/problems/valid-binary-search-tree",
        "difficulty": "medium",
        "last_reviewed": null,
        "sr_score": 0,
        "attempted": false
    },
    {
        "id": 84,
        "name": "Kth Smallest Integer in BST",
        "url": "https://neetcode.io/problems/kth-smallest-integer-in-bst",
        "difficulty": "medium",
        "last_reviewed": null,
        "sr_score": 0,
        "attempted": false
    },
    {
        "id": 85,
        "name": "Construct Binary Tree from Preorder and Inorder Traversal",
        "url": "https://neetcode.io/problems/binary-tree-from-preorder-and-inorder-traversal",
        "difficulty": "medium",
        "last_reviewed": null,
        "sr_score": 0,
        "attempted": false
    },
    {
        "id": 86,
        "name": "Binary Tree Maximum Path Sum",
        "url": "https://neetcode.io/problems/binary-tree-maximum-path-sum",
        "difficulty": "hard",
        "last_reviewed": null,
        "sr_score": 0,
        "attempted": false
    },
    {
        "id": 87,
        "name": "Serialize and Deserialize Binary Tree",
        "url": "https://neetcode.io/problems/serialize-and-deserialize-binary-tree",
        "difficulty": "hard",
        "last_reviewed": null,
        "sr_score": 0,
        "attempted": false
    },
    {
        "id": 88,
        "name": "Valid Sudoku",
        "url": "https://neetcode.io/problems/valid-sudoku",
        "difficulty": "medium",
        "last_reviewed": null,
        "sr_score": 0,
        "attempted": false
    },
    {
        "id": 89,
        "name": "Two Integer Sum II",
        "url": "https://neetcode.io/problems/two-integer-sum-ii",
        "difficulty": "medium",
        "last_reviewed": null,
        "sr_score": 0,
        "attempted": false
    },
    {
        "id": 90,
        "name": "Trapping Rain Water",
        "url": "https://neetcode.io/problems/trapping-rain-water",
        "difficulty": "hard",
        "last_reviewed": null,
        "sr_score": 0,
        "attempted": false
    },
    {
        "id": 91,
        "name": "Permutation in String",
        "url": "https://neetcode.io/problems/permutation-string",
        "difficulty": "medium",
        "last_reviewed": null,
        "sr_score": 0,
        "attempted": false
    },
    {
        "id": 92,
        "name": "Sliding Window Maximum",
        "url": "https://neetcode.io/problems/sliding-window-maximum",
        "difficulty": "hard",
        "last_reviewed": null,
        "sr_score": 0,
        "attempted": false
    },
    {
        "id": 93,
        "name": "Minimum Stack",
        "url": "https://neetcode.io/problems/minimum-stack",
        "difficulty": "medium",
        "last_reviewed": null,
        "sr_score": 0,
        "attempted": false
    },
    {
        "id": 94,
        "name": "Evaluate Reverse Polish Notation",
        "url": "https://neetcode.io/problems/evaluate-reverse-polish-notation",
        "difficulty": "medium",
        "last_reviewed": null,
        "sr_score": 0,
        "attempted": false
    },
    {
        "id": 95,
        "name": "Generate Parentheses",
        "url": "https://neetcode.io/problems/generate-parentheses",
        "difficulty": "medium",
        "last_reviewed": null,
        "sr_score": 0,
        "attempted": false
    },
    {
        "id": 96,
        "name": "Daily Temperatures",
        "url": "https://neetcode.io/problems/daily-temperatures",
        "difficulty": "medium",
        "last_reviewed": null,
        "sr_score": 0,
        "attempted": false
    },
    {
        "id": 97,
        "name": "Car Fleet",
        "url": "https://neetcode.io/problems/car-fleet",
        "difficulty": "medium",
        "last_reviewed": null,
        "sr_score": 0,
        "attempted": false
    },
    {
        "id": 98,
        "name": "Largest Rectangle In Histogram",
        "url": "https://neetcode.io/problems/largest-rectangle-in-histogram",
        "difficulty": "hard",
        "last_reviewed": null,
        "sr_score": 0,
        "attempted": false
    },
    {
        "id": 99,
        "name": "Binary Search",
        "url": "https://neetcode.io/problems/binary-search",
        "difficulty": "easy",
        "last_reviewed": null,
        "sr_score": 0,
        "attempted": false
    },
    {
        "id": 100,
        "name": "Search a 2D Matrix",
        "url": "https://neetcode.io/problems/search-2d-matrix",
        "difficulty": "medium",
        "last_reviewed": null,
        "sr_score": 0,
        "attempted": false
    },
    {
        "id": 101,
        "name": "Koko Eating Bananas",
        "url": "https://neetcode.io/problems/eating-bananas",
        "difficulty": "medium",
        "last_reviewed": null,
        "sr_score": 0,
        "attempted": false
    },
    {
        "id": 102,
        "name": "Time Based Key-Value Store",
        "url": "https://neetcode.io/problems/time-based-key-value-store",
        "difficulty": "medium",
        "last_reviewed": null,
        "sr_score": 0,
        "attempted": false
    },
    {
        "id": 103,
        "name": "Median of Two Sorted Arrays",
        "url": "https://neetcode.io/problems/median-of-two-sorted-arrays",
        "difficulty": "hard",
        "last_reviewed": null,
        "sr_score": 0,
        "attempted": false
    },
    {
        "id": 104,
        "name": "Copy Linked List with Random Pointer",
        "url": "https://neetcode.io/problems/copy-linked-list-with-random-pointer",
        "difficulty": "medium",
        "last_reviewed": null,
        "sr_score": 0,
        "attempted": false
    },
    {
        "id": 105,
        "name": "Add Two Numbers",
        "url": "https://neetcode.io/problems/add-two-numbers",
        "difficulty": "medium",
        "last_reviewed": null,
        "sr_score": 0,
        "attempted": false
    },
    {
        "id": 106,
        "name": "Find the Duplicate Number",
        "url": "https://neetcode.io/problems/find-duplicate-integer",
        "difficulty": "medium",
        "last_reviewed": null,
        "sr_score": 0,
        "attempted": false
    },
    {
        "id": 107,
        "name": "LRU Cache",
        "url": "https://neetcode.io/problems/lru-cache",
        "difficulty": "medium",
        "last_reviewed": null,
        "sr_score": 0,
        "attempted": false
    },
    {
        "id": 108,
        "name": "Reverse Nodes in K-Group",
        "url": "https://neetcode.io/problems/reverse-nodes-in-k-group",
        "difficulty": "hard",
        "last_reviewed": null,
        "sr_score": 0,
        "attempted": false
    },
    {
        "id": 109,
        "name": "Diameter of Binary Tree",
        "url": "https://neetcode.io/problems/binary-tree-diameter",
        "difficulty": "easy",
        "last_reviewed": null,
        "sr_score": 0,
        "attempted": false
    },
    {
        "id": 110,
        "name": "Balanced Binary Tree",
        "url": "https://neetcode.io/problems/balanced-binary-tree",
        "difficulty": "easy",
        "last_reviewed": null,
        "sr_score": 0,
        "attempted": false
    },
    {
        "id": 111,
        "name": "Binary Tree Right Side View",
        "url": "https://neetcode.io/problems/binary-tree-right-side-view",
        "difficulty": "medium",
        "last_reviewed": null,
        "sr_score": 0,
        "attempted": false
    },
    {
        "id": 112,
        "name": "Count Good Nodes in Binary Tree",
        "url": "https://neetcode.io/problems/count-good-nodes-in-binary-tree",
        "difficulty": "medium",
        "last_reviewed": null,
        "sr_score": 0,
        "attempted": false
    },
    {
        "id": 113,
        "name": "Kth Largest Element in a Stream",
        "url": "https://neetcode.io/problems/kth-largest-integer-in-a-stream",
        "difficulty": "easy",
        "last_reviewed": null,
        "sr_score": 0,
        "attempted": false
    },
    {
        "id": 114,
        "name": "Last Stone Weight",
        "url": "https://neetcode.io/problems/last-stone-weight",
        "difficulty": "easy",
        "last_reviewed": null,
        "sr_score": 0,
        "attempted": false
    },
    {
        "id": 115,
        "name": "K Closest Points to Origin",
        "url": "https://neetcode.io/problems/k-closest-points-to-origin",
        "difficulty": "medium",
        "last_reviewed": null,
        "sr_score": 0,
        "attempted": false
    },
    {
        "id": 116,
        "name": "Kth Largest Element in an Array",
        "url": "https://neetcode.io/problems/kth-largest-element-in-an-array",
        "difficulty": "medium",
        "last_reviewed": null,
        "sr_score": 0,
        "attempted": false
    },
    {
        "id": 117,
        "name": "Task Scheduler",
        "url": "https://neetcode.io/problems/task-scheduling",
        "difficulty": "medium",
        "last_reviewed": null,
        "sr_score": 0,
        "attempted": false
    },
    {
        "id": 118,
        "name": "Design Twitter",
        "url": "https://neetcode.io/problems/design-twitter-feed",
        "difficulty": "medium",
        "last_reviewed": null,
        "sr_score": 0,
        "attempted": false
    },
    {
        "id": 119,
        "name": "Subsets",
        "url": "https://neetcode.io/problems/subsets",
        "difficulty": "medium",
        "last_reviewed": null,
        "sr_score": 0,
        "attempted": false
    },
    {
        "id": 120,
        "name": "Permutations",
        "url": "https://neetcode.io/problems/permutations",
        "difficulty": "medium",
        "last_reviewed": null,
        "sr_score": 0,
        "attempted": false
    },
    {
        "id": 121,
        "name": "Subsets II",
        "url": "https://neetcode.io/problems/subsets-ii",
        "difficulty": "medium",
        "last_reviewed": null,
        "sr_score": 0,
        "attempted": false
    },
    {
        "id": 122,
        "name": "Combination Sum II",
        "url": "https://neetcode.io/problems/combination-target-sum-ii",
        "difficulty": "medium",
        "last_reviewed": null,
        "sr_score": 0,
        "attempted": false
    },
    {
        "id": 123,
        "name": "Palindrome Partitioning",
        "url": "https://neetcode.io/problems/palindrome-partitioning",
        "difficulty": "medium",
        "last_reviewed": null,
        "sr_score": 0,
        "attempted": false
    },
    {
        "id": 124,
        "name": "Letter Combinations of a Phone Number",
        "url": "https://neetcode.io/problems/combinations-of-a-phone-number",
        "difficulty": "medium",
        "last_reviewed": null,
        "sr_score": 0,
        "attempted": false
    },
    {
        "id": 125,
        "name": "N-Queens",
        "url": "https://neetcode.io/problems/n-queens",
        "difficulty": "hard",
        "last_reviewed": null,
        "sr_score": 0,
        "attempted": false
    },
    {
        "id": 126,
        "name": "Max Area of Island",
        "url": "https://neetcode.io/problems/max-area-of-island",
        "difficulty": "medium",
        "last_reviewed": null,
        "sr_score": 0,
        "attempted": false
    },
    {
        "id": 127,
        "name": "Surrounded Regions",
        "url": "https://neetcode.io/problems/surrounded-regions",
        "difficulty": "medium",
        "last_reviewed": null,
        "sr_score": 0,
        "attempted": false
    },
    {
        "id": 128,
        "name": "Rotting Fruit",
        "url": "https://neetcode.io/problems/rotting-fruit",
        "difficulty": "medium",
        "last_reviewed": null,
        "sr_score": 0,
        "attempted": false
    },
    {
        "id": 129,
        "name": "Course Schedule II",
        "url": "https://neetcode.io/problems/course-schedule-ii",
        "difficulty": "medium",
        "last_reviewed": null,
        "sr_score": 0,
        "attempted": false
    },
    {
        "id": 130,
        "name": "Redundant Connection",
        "url": "https://neetcode.io/problems/redundant-connection",
        "difficulty": "medium",
        "last_reviewed": null,
        "sr_score": 0,
        "attempted": false
    },
    {
        "id": 131,
        "name": "Word Ladder",
        "url": "https://neetcode.io/problems/word-ladder",
        "difficulty": "hard",
        "last_reviewed": null,
        "sr_score": 0,
        "attempted": false
    },
    {
        "id": 132,
        "name": "Reconstruct Flight Path",
        "url": "https://neetcode.io/problems/reconstruct-flight-path",
        "difficulty": "hard",
        "last_reviewed": null,
        "sr_score": 0,
        "attempted": false
    },
    {
        "id": 133,
        "name": "Min Cost to Connect Points",
        "url": "https://neetcode.io/problems/min-cost-to-connect-points",
        "difficulty": "medium",
        "last_reviewed": null,
        "sr_score": 0,
        "attempted": false
    },
    {
        "id": 134,
        "name": "Network Delay Time",
        "url": "https://neetcode.io/problems/network-delay-time",
        "difficulty": "medium",
        "last_reviewed": null,
        "sr_score": 0,
        "attempted": false
    },
    {
        "id": 135,
        "name": "Swim in Rising Water",
        "url": "https://neetcode.io/problems/swim-in-rising-water",
        "difficulty": "hard",
        "last_reviewed": null,
        "sr_score": 0,
        "attempted": false
    },
    {
        "id": 136,
        "name": "Cheapest Flights Within K Stops",
        "url": "https://neetcode.io/problems/cheapest-flight-path",
        "difficulty": "medium",
        "last_reviewed": null,
        "sr_score": 0,
        "attempted": false
    },
    {
        "id": 137,
        "name": "Min Cost Climbing Stairs",
        "url": "https://neetcode.io/problems/min-cost-climbing-stairs",
        "difficulty": "easy",
        "last_reviewed": null,
        "sr_score": 0,
        "attempted": false
    },
    {
        "id": 138,
        "name": "Partition Equal Subset Sum",
        "url": "https://neetcode.io/problems/partition-equal-subset-sum",
        "difficulty": "medium",
        "last_reviewed": null,
        "sr_score": 0,
        "attempted": false
    },
    {
        "id": 139,
        "name": "Best Time to Buy and Sell Stock with Cooldown",
        "url": "https://neetcode.io/problems/buy-and-sell-crypto-with-cooldown",
        "difficulty": "medium",
        "last_reviewed": null,
        "sr_score": 0,
        "attempted": false
    },
    {
        "id": 140,
        "name": "Coin Change II",
        "url": "https://neetcode.io/problems/coin-change-ii",
        "difficulty": "medium",
        "last_reviewed": null,
        "sr_score": 0,
        "attempted": false
    },
    {
        "id": 141,
        "name": "Target Sum",
        "url": "https://neetcode.io/problems/target-sum",
        "difficulty": "medium",
        "last_reviewed": null,
        "sr_score": 0,
        "attempted": false
    },
    {
        "id": 142,
        "name": "Interleaving String",
        "url": "https://neetcode.io/problems/interleaving-string",
        "difficulty": "medium",
        "last_reviewed": null,
        "sr_score": 0,
        "attempted": false
    },
    {
        "id": 143,
        "name": "Longest Increasing Path in Matrix",
        "url": "https://neetcode.io/problems/longest-increasing-path-in-matrix",
        "difficulty": "hard",
        "last_reviewed": null,
        "sr_score": 0,
        "attempted": false
    },
    {
        "id": 144,
        "name": "Distinct Subsequences",
        "url": "https://neetcode.io/problems/count-subsequences",
        "difficulty": "hard",
        "last_reviewed": null,
        "sr_score": 0,
        "attempted": false
    },
    {
        "id": 145,
        "name": "Edit Distance",
        "url": "https://neetcode.io/problems/edit-distance",
        "difficulty": "medium",
        "last_reviewed": null,
        "sr_score": 0,
        "attempted": false
    },
    {
        "id": 146,
        "name": "Burst Balloons",
        "url": "https://neetcode.io/problems/burst-balloons",
        "difficulty": "hard",
        "last_reviewed": null,
        "sr_score": 0,
        "attempted": false
    },
    {
        "id": 147,
        "name": "Regular Expression Matching",
        "url": "https://neetcode.io/problems/regular-expression-matching",
        "difficulty": "hard",
        "last_reviewed": null,
        "sr_score": 0,
        "attempted": false
    },
    {
        "id": 148,
        "name": "Jump Game II",
        "url": "https://neetcode.io/problems/jump-game-ii",
        "difficulty": "medium",
        "last_reviewed": null,
        "sr_score": 0,
        "attempted": false
    },
    {
        "id": 149,
        "name": "Gas Station",
        "url": "https://neetcode.io/problems/gas-station",
        "difficulty": "medium",
        "last_reviewed": null,
        "sr_score": 0,
        "attempted": false
    },
    {
        "id": 150,
        "name": "Hand of Straights",
        "url": "https://neetcode.io/problems/hand-of-straights",
        "difficulty": "medium",
        "last_reviewed": null,
        "sr_score": 0,
        "attempted": false
    },
    {
        "id": 151,
        "name": "Merge Triplets to Form Target",
        "url": "https://neetcode.io/problems/merge-triplets-to-form-target",
        "difficulty": "medium",
        "last_reviewed": null,
        "sr_score": 0,
        "attempted": false
    },
    {
        "id": 152,
        "name": "Partition Labels",
        "url": "https://neetcode.io/problems/partition-labels",
        "difficulty": "medium",
        "last_reviewed": null,
        "sr_score": 0,
        "attempted": false
    },
    {
        "id": 153,
        "name": "Valid Parenthesis String",
        "url": "https://neetcode.io/problems/valid-parenthesis-string",
        "difficulty": "medium",
        "last_reviewed": null,
        "sr_score": 0,
        "attempted": false
    },
    {
        "id": 154,
        "name": "Minimum Interval to Include Each Query",
        "url": "https://neetcode.io/problems/minimum-interval-including-query",
        "difficulty": "hard",
        "last_reviewed": null,
        "sr_score": 0,
        "attempted": false
    },
    {
        "id": 155,
        "name": "Non-Cyclical Number",
        "url": "https://neetcode.io/problems/non-cyclical-number",
        "difficulty": "easy",
        "last_reviewed": null,
        "sr_score": 0,
        "attempted": false
    },
    {
        "id": 156,
        "name": "Plus One",
        "url": "https://neetcode.io/problems/plus-one",
        "difficulty": "easy",
        "last_reviewed": null,
        "sr_score": 0,
        "attempted": false
    },
    {
        "id": 157,
        "name": "Pow(x, n)",
        "url": "https://neetcode.io/problems/pow-x-n",
        "difficulty": "medium",
        "last_reviewed": null,
        "sr_score": 0,
        "attempted": false
    },
    {
        "id": 158,
        "name": "Multiply Strings",
        "url": "https://neetcode.io/problems/multiply-strings",
        "difficulty": "medium",
        "last_reviewed": null,
        "sr_score": 0,
        "attempted": false
    },
    {
        "id": 159,
        "name": "Detect Squares",
        "url": "https://neetcode.io/problems/count-squares",
        "difficulty": "medium",
        "last_reviewed": null,
        "sr_score": 0,
        "attempted": false
    },
    {
        "id": 160,
        "name": "Single Number",
        "url": "https://neetcode.io/problems/single-number",
        "difficulty": "easy",
        "last_reviewed": null,
        "sr_score": 0,
        "attempted": false
    },
    {
        "id": 161,
        "name": "Reverse Integer",
        "url": "https://neetcode.io/problems/reverse-integer",
        "difficulty": "medium",
        "last_reviewed": null,
        "sr_score": 0,
        "attempted": false
    },
    {
        "id": 162,
        "name": "Minimum Remove to make Valid Parentheses",
        "url": "https://neetcode.io/problems/minimum-remove-to-make-valid-parentheses",
        "difficulty": "medium",
        "last_reviewed": null,
        "sr_score": 0,
        "attempted": false
    },
    {
        "id": 163,
        "name": "Valid Palindrome II",
        "url": "https://neetcode.io/problems/valid-palindrome-ii",
        "difficulty": "easy",
        "last_reviewed": null,
        "sr_score": 0,
        "attempted": false
    },
    {
        "id": 164,
        "name": "Binary Tree Vertical Order Traversal",
        "url": "https://neetcode.io/problems/binary-tree-vertical-order-traversal",
        "difficulty": "medium",
        "last_reviewed": null,
        "sr_score": 0,
        "attempted": false
    },
    {
        "id": 165,
        "name": "Valid Word Abbreviation",
        "url": "https://neetcode.io/problems/valid-word-abbreviation",
        "difficulty": "easy",
        "last_reviewed": null,
        "sr_score": 0,
        "attempted": false
    },
    {
        "id": 166,
        "name": "Buildings With an Ocean View",
        "url": "https://neetcode.io/problems/buildings-with-an-ocean-view",
        "difficulty": "medium",
        "last_reviewed": null,
        "sr_score": 0,
        "attempted": false
    },
    {
        "id": 167,
        "name": "Reorganize String",
        "url": "https://neetcode.io/problems/reorganize-string",
        "difficulty": "medium",
        "last_reviewed": null,
        "sr_score": 0,
        "attempted": false
    },
    {
        "id": 168,
        "name": "Maximum Profit in Job Scheduling",
        "url": "https://neetcode.io/problems/maximum-profit-in-job-scheduling",
        "difficulty": "hard",
        "last_reviewed": null,
        "sr_score": 0,
        "attempted": false
    },
    {
        "id": 169,
        "name": "Put Marbles in Bags",
        "url": "https://neetcode.io/problems/put-marbles-in-bags",
        "difficulty": "hard",
        "last_reviewed": null,
        "sr_score": 0,
        "attempted": false
    },
    {
        "id": 170,
        "name": "Analyze User Website Visit Pattern",
        "url": "https://neetcode.io/problems/analyze-user-website-visit-pattern",
        "difficulty": "medium",
        "last_reviewed": null,
        "sr_score": 0,
        "attempted": false
    },
    {
        "id": 171,
        "name": "Merge Strings Alternately",
        "url": "https://neetcode.io/problems/merge-strings-alternately",
        "difficulty": "easy",
        "last_reviewed": null,
        "sr_score": 0,
        "attempted": false
    },
    {
        "id": 172,
        "name": "Merge Sorted Array",
        "url": "https://neetcode.io/problems/merge-sorted-array",
        "difficulty": "easy",
        "last_reviewed": null,
        "sr_score": 0,
        "attempted": false
    },
    {
        "id": 173,
        "name": "Concatenation of Array",
        "url": "https://neetcode.io/problems/concatenation-of-array",
        "difficulty": "easy",
        "last_reviewed": null,
        "sr_score": 0,
        "attempted": false
    },
    {
        "id": 174,
        "name": "Longest Common Prefix",
        "url": "https://neetcode.io/problems/longest-common-prefix",
        "difficulty": "easy",
        "last_reviewed": null,
        "sr_score": 0,
        "attempted": false
    },
    {
        "id": 175,
        "name": "Remove Element",
        "url": "https://neetcode.io/problems/remove-element",
        "difficulty": "easy",
        "last_reviewed": null,
        "sr_score": 0,
        "attempted": false
    },
    {
        "id": 176,
        "name": "Majority Element",
        "url": "https://neetcode.io/problems/majority-element",
        "difficulty": "easy",
        "last_reviewed": null,
        "sr_score": 0,
        "attempted": false
    },
    {
        "id": 177,
        "name": "Sort an Array",
        "url": "https://neetcode.io/problems/sort-an-array",
        "difficulty": "medium",
        "last_reviewed": null,
        "sr_score": 0,
        "attempted": false
    },
    {
        "id": 178,
        "name": "Sort Colors",
        "url": "https://neetcode.io/problems/sort-colors",
        "difficulty": "medium",
        "last_reviewed": null,
        "sr_score": 0,
        "attempted": false
    },
    {
        "id": 179,
        "name": "Subarray Sum Equals K",
        "url": "https://neetcode.io/problems/subarray-sum-equals-k",
        "difficulty": "medium",
        "last_reviewed": null,
        "sr_score": 0,
        "attempted": false
    },
    {
        "id": 180,
        "name": "Best Time to Buy and Sell Stock II",
        "url": "https://neetcode.io/problems/best-time-to-buy-and-sell-stock-ii",
        "difficulty": "medium",
        "last_reviewed": null,
        "sr_score": 0,
        "attempted": false
    },
    {
        "id": 181,
        "name": "Rotate Array",
        "url": "https://neetcode.io/problems/rotate-array",
        "difficulty": "medium",
        "last_reviewed": null,
        "sr_score": 0,
        "attempted": false
    },
    {
        "id": 182,
        "name": "Majority Element II",
        "url": "https://neetcode.io/problems/majority-element-ii",
        "difficulty": "medium",
        "last_reviewed": null,
        "sr_score": 0,
        "attempted": false
    },
    {
        "id": 183,
        "name": "First Missing Positive",
        "url": "https://neetcode.io/problems/first-missing-positive",
        "difficulty": "hard",
        "last_reviewed": null,
        "sr_score": 0,
        "attempted": false
    },
    {
        "id": 184,
        "name": "Boats to Save People",
        "url": "https://neetcode.io/problems/boats-to-save-people",
        "difficulty": "medium",
        "last_reviewed": null,
        "sr_score": 0,
        "attempted": false
    },
    {
        "id": 185,
        "name": "Reverse String",
        "url": "https://neetcode.io/problems/reverse-string",
        "difficulty": "easy",
        "last_reviewed": null,
        "sr_score": 0,
        "attempted": false
    },
    {
        "id": 186,
        "name": "Remove Duplicates From Sorted Array",
        "url": "https://neetcode.io/problems/remove-duplicates-from-sorted-array",
        "difficulty": "easy",
        "last_reviewed": null,
        "sr_score": 0,
        "attempted": false
    },
    {
        "id": 187,
        "name": "4Sum",
        "url": "https://neetcode.io/problems/4sum",
        "difficulty": "medium",
        "last_reviewed": null,
        "sr_score": 0,
        "attempted": false
    },
    {
        "id": 188,
        "name": "Contains Duplicate II",
        "url": "https://neetcode.io/problems/contains-duplicate-ii",
        "difficulty": "easy",
        "last_reviewed": null,
        "sr_score": 0,
        "attempted": false
    },
    {
        "id": 189,
        "name": "Minimum Size Subarray Sum",
        "url": "https://neetcode.io/problems/minimum-size-subarray-sum",
        "difficulty": "medium",
        "last_reviewed": null,
        "sr_score": 0,
        "attempted": false
    },
    {
        "id": 190,
        "name": "Find K Closest Elements",
        "url": "https://neetcode.io/problems/find-k-closest-elements",
        "difficulty": "medium",
        "last_reviewed": null,
        "sr_score": 0,
        "attempted": false
    },
    {
        "id": 191,
        "name": "Baseball Game",
        "url": "https://neetcode.io/problems/baseball-game",
        "difficulty": "easy",
        "last_reviewed": null,
        "sr_score": 0,
        "attempted": false
    },
    {
        "id": 192,
        "name": "Asteroid Collision",
        "url": "https://neetcode.io/problems/asteroid-collision",
        "difficulty": "medium",
        "last_reviewed": null,
        "sr_score": 0,
        "attempted": false
    },
    {
        "id": 193,
        "name": "Simplify Path",
        "url": "https://neetcode.io/problems/simplify-path",
        "difficulty": "medium",
        "last_reviewed": null,
        "sr_score": 0,
        "attempted": false
    },
    {
        "id": 194,
        "name": "Decode String",
        "url": "https://neetcode.io/problems/decode-string",
        "difficulty": "medium",
        "last_reviewed": null,
        "sr_score": 0,
        "attempted": false
    },
    {
        "id": 195,
        "name": "Search Insert Position",
        "url": "https://neetcode.io/problems/search-insert-position",
        "difficulty": "easy",
        "last_reviewed": null,
        "sr_score": 0,
        "attempted": false
    },
    {
        "id": 196,
        "name": "Sqrt(x)",
        "url": "https://neetcode.io/problems/sqrtx",
        "difficulty": "easy",
        "last_reviewed": null,
        "sr_score": 0,
        "attempted": false
    },
    {
        "id": 197,
        "name": "Capacity to Ship Packages Within D Days",
        "url": "https://neetcode.io/problems/capacity-to-ship-packages-within-d-days",
        "difficulty": "medium",
        "last_reviewed": null,
        "sr_score": 0,
        "attempted": false
    },
    {
        "id": 198,
        "name": "Search in Rotated Sorted Array II",
        "url": "https://neetcode.io/problems/search-in-rotated-sorted-array-ii",
        "difficulty": "medium",
        "last_reviewed": null,
        "sr_score": 0,
        "attempted": false
    },
    {
        "id": 199,
        "name": "Split Array Largest Sum",
        "url": "https://neetcode.io/problems/split-array-largest-sum",
        "difficulty": "hard",
        "last_reviewed": null,
        "sr_score": 0,
        "attempted": false
    },
    {
        "id": 200,
        "name": "Guess Number Higher Or Lower",
        "url": "https://neetcode.io/problems/guess-number-higher-or-lower",
        "difficulty": "easy",
        "last_reviewed": null,
        "sr_score": 0,
        "attempted": false
    },
    {
        "id": 201,
        "name": "Find in Mountain Array",
        "url": "https://neetcode.io/problems/find-in-mountain-array",
        "difficulty": "hard",
        "last_reviewed": null,
        "sr_score": 0,
        "attempted": false
    },
    {
        "id": 202,
        "name": "Reverse Linked List II",
        "url": "https://neetcode.io/problems/reverse-linked-list-ii",
        "difficulty": "medium",
        "last_reviewed": null,
        "sr_score": 0,
        "attempted": false
    },
    {
        "id": 203,
        "name": "Binary Tree Inorder Traversal",
        "url": "https://neetcode.io/problems/binary-tree-inorder-traversal",
        "difficulty": "easy",
        "last_reviewed": null,
        "sr_score": 0,
        "attempted": false
    },
    {
        "id": 204,
        "name": "Binary Tree Preorder Traversal",
        "url": "https://neetcode.io/problems/binary-tree-preorder-traversal",
        "difficulty": "easy",
        "last_reviewed": null,
        "sr_score": 0,
        "attempted": false
    },
    {
        "id": 205,
        "name": "Binary Tree Postorder Traversal",
        "url": "https://neetcode.io/problems/binary-tree-postorder-traversal",
        "difficulty": "easy",
        "last_reviewed": null,
        "sr_score": 0,
        "attempted": false
    },
    {
        "id": 206,
        "name": "Insert into a Binary Search Tree",
        "url": "https://neetcode.io/problems/insert-into-a-binary-search-tree",
        "difficulty": "medium",
        "last_reviewed": null,
        "sr_score": 0,
        "attempted": false
    },
    {
        "id": 207,
        "name": "Delete Node in a BST",
        "url": "https://neetcode.io/problems/delete-node-in-a-bst",
        "difficulty": "medium",
        "last_reviewed": null,
        "sr_score": 0,
        "attempted": false
    },
    {
        "id": 208,
        "name": "House Robber III",
        "url": "https://neetcode.io/problems/house-robber-iii",
        "difficulty": "medium",
        "last_reviewed": null,
        "sr_score": 0,
        "attempted": false
    },
    {
        "id": 209,
        "name": "Delete Leaves With a Given Value",
        "url": "https://neetcode.io/problems/delete-leaves-with-a-given-value",
        "difficulty": "medium",
        "last_reviewed": null,
        "sr_score": 0,
        "attempted": false
    },
    {
        "id": 210,
        "name": "Construct Quad Tree",
        "url": "https://neetcode.io/problems/construct-quad-tree",
        "difficulty": "medium",
        "last_reviewed": null,
        "sr_score": 0,
        "attempted": false
    },
    {
        "id": 211,
        "name": "Single Threaded CPU",
        "url": "https://neetcode.io/problems/single-threaded-cpu",
        "difficulty": "medium",
        "last_reviewed": null,
        "sr_score": 0,
        "attempted": false
    },
    {
        "id": 212,
        "name": "Longest Happy String",
        "url": "https://neetcode.io/problems/longest-happy-string",
        "difficulty": "medium",
        "last_reviewed": null,
        "sr_score": 0,
        "attempted": false
    },
    {
        "id": 213,
        "name": "Car Pooling",
        "url": "https://neetcode.io/problems/car-pooling",
        "difficulty": "medium",
        "last_reviewed": null,
        "sr_score": 0,
        "attempted": false
    },
    {
        "id": 214,
        "name": "IPO",
        "url": "https://neetcode.io/problems/ipo",
        "difficulty": "hard",
        "last_reviewed": null,
        "sr_score": 0,
        "attempted": false
    },
    {
        "id": 215,
        "name": "Sum of All Subsets XOR Total",
        "url": "https://neetcode.io/problems/sum-of-all-subset-xor-totals",
        "difficulty": "easy",
        "last_reviewed": null,
        "sr_score": 0,
        "attempted": false
    },
    {
        "id": 216,
        "name": "Combinations",
        "url": "https://neetcode.io/problems/combinations",
        "difficulty": "medium",
        "last_reviewed": null,
        "sr_score": 0,
        "attempted": false
    },
    {
        "id": 217,
        "name": "Permutations II",
        "url": "https://neetcode.io/problems/permutations-ii",
        "difficulty": "medium",
        "last_reviewed": null,
        "sr_score": 0,
        "attempted": false
    },
    {
        "id": 218,
        "name": "Matchsticks to Square",
        "url": "https://neetcode.io/problems/matchsticks-to-square",
        "difficulty": "medium",
        "last_reviewed": null,
        "sr_score": 0,
        "attempted": false
    },
    {
        "id": 219,
        "name": "Partition to K Equal Sum Subsets",
        "url": "https://neetcode.io/problems/partition-to-k-equal-sum-subsets",
        "difficulty": "medium",
        "last_reviewed": null,
        "sr_score": 0,
        "attempted": false
    },
    {
        "id": 220,
        "name": "N-Queens II",
        "url": "https://neetcode.io/problems/n-queens-ii",
        "difficulty": "hard",
        "last_reviewed": null,
        "sr_score": 0,
        "attempted": false
    },
    {
        "id": 221,
        "name": "Word Break II",
        "url": "https://neetcode.io/problems/word-break-ii",
        "difficulty": "hard",
        "last_reviewed": null,
        "sr_score": 0,
        "attempted": false
    },
    {
        "id": 222,
        "name": "Extra Characters in a String",
        "url": "https://neetcode.io/problems/extra-characters-in-a-string",
        "difficulty": "medium",
        "last_reviewed": null,
        "sr_score": 0,
        "attempted": false
    },
    {
        "id": 223,
        "name": "Island Perimeter",
        "url": "https://neetcode.io/problems/island-perimeter",
        "difficulty": "easy",
        "last_reviewed": null,
        "sr_score": 0,
        "attempted": false
    },
    {
        "id": 224,
        "name": "Verifying An Alien Dictionary",
        "url": "https://neetcode.io/problems/verifying-an-alien-dictionary",
        "difficulty": "easy",
        "last_reviewed": null,
        "sr_score": 0,
        "attempted": false
    },
    {
        "id": 225,
        "name": "Find the Town Judge",
        "url": "https://neetcode.io/problems/find-the-town-judge",
        "difficulty": "easy",
        "last_reviewed": null,
        "sr_score": 0,
        "attempted": false
    },
    {
        "id": 226,
        "name": "Open The Lock",
        "url": "https://neetcode.io/problems/open-the-lock",
        "difficulty": "medium",
        "last_reviewed": null,
        "sr_score": 0,
        "attempted": false
    },
    {
        "id": 227,
        "name": "Course Schedule IV",
        "url": "https://neetcode.io/problems/course-schedule-iv",
        "difficulty": "medium",
        "last_reviewed": null,
        "sr_score": 0,
        "attempted": false
    },
    {
        "id": 228,
        "name": "Accounts Merge",
        "url": "https://neetcode.io/problems/accounts-merge",
        "difficulty": "medium",
        "last_reviewed": null,
        "sr_score": 0,
        "attempted": false
    },
    {
        "id": 229,
        "name": "Evaluate Division",
        "url": "https://neetcode.io/problems/evaluate-division",
        "difficulty": "medium",
        "last_reviewed": null,
        "sr_score": 0,
        "attempted": false
    },
    {
        "id": 230,
        "name": "Path with Minimum Effort",
        "url": "https://neetcode.io/problems/path-with-minimum-effort",
        "difficulty": "medium",
        "last_reviewed": null,
        "sr_score": 0,
        "attempted": false
    },
    {
        "id": 231,
        "name": "Greatest Common Divisor Traversal",
        "url": "https://neetcode.io/problems/greatest-common-divisor-traversal",
        "difficulty": "hard",
        "last_reviewed": null,
        "sr_score": 0,
        "attempted": false
    },
    {
        "id": 232,
        "name": "N-th Tribonacci Number",
        "url": "https://neetcode.io/problems/n-th-tribonacci-number",
        "difficulty": "easy",
        "last_reviewed": null,
        "sr_score": 0,
        "attempted": false
    },
    {
        "id": 233,
        "name": "Combination Sum IV",
        "url": "https://neetcode.io/problems/combination-sum-iv",
        "difficulty": "medium",
        "last_reviewed": null,
        "sr_score": 0,
        "attempted": false
    },
    {
        "id": 234,
        "name": "Perfect Squares",
        "url": "https://neetcode.io/problems/perfect-squares",
        "difficulty": "medium",
        "last_reviewed": null,
        "sr_score": 0,
        "attempted": false
    },
    {
        "id": 235,
        "name": "Integer Break",
        "url": "https://neetcode.io/problems/integer-break",
        "difficulty": "medium",
        "last_reviewed": null,
        "sr_score": 0,
        "attempted": false
    },
    {
        "id": 236,
        "name": "Stone Game III",
        "url": "https://neetcode.io/problems/stone-game-iii",
        "difficulty": "hard",
        "last_reviewed": null,
        "sr_score": 0,
        "attempted": false
    },
    {
        "id": 237,
        "name": "Unique Paths II",
        "url": "https://neetcode.io/problems/unique-paths-ii",
        "difficulty": "medium",
        "last_reviewed": null,
        "sr_score": 0,
        "attempted": false
    },
    {
        "id": 238,
        "name": "Minimum Path Sum",
        "url": "https://neetcode.io/problems/minimum-path-sum",
        "difficulty": "medium",
        "last_reviewed": null,
        "sr_score": 0,
        "attempted": false
    },
    {
        "id": 239,
        "name": "Last Stone Weight II",
        "url": "https://neetcode.io/problems/last-stone-weight-ii",
        "difficulty": "medium",
        "last_reviewed": null,
        "sr_score": 0,
        "attempted": false
    },
    {
        "id": 240,
        "name": "Stone Game",
        "url": "https://neetcode.io/problems/stone-game",
        "difficulty": "medium",
        "last_reviewed": null,
        "sr_score": 0,
        "attempted": false
    },
    {
        "id": 241,
        "name": "Stone Game II",
        "url": "https://neetcode.io/problems/stone-game-ii",
        "difficulty": "medium",
        "last_reviewed": null,
        "sr_score": 0,
        "attempted": false
    },
    {
        "id": 242,
        "name": "Lemonade Change",
        "url": "https://neetcode.io/problems/lemonade-change",
        "difficulty": "easy",
        "last_reviewed": null,
        "sr_score": 0,
        "attempted": false
    },
    {
        "id": 243,
        "name": "Maximum Sum Circular Subarray",
        "url": "https://neetcode.io/problems/maximum-sum-circular-subarray",
        "difficulty": "medium",
        "last_reviewed": null,
        "sr_score": 0,
        "attempted": false
    },
    {
        "id": 244,
        "name": "Longest Turbulent Subarray",
        "url": "https://neetcode.io/problems/longest-turbulent-subarray",
        "difficulty": "medium",
        "last_reviewed": null,
        "sr_score": 0,
        "attempted": false
    },
    {
        "id": 245,
        "name": "Jump Game VII",
        "url": "https://neetcode.io/problems/jump-game-vii",
        "difficulty": "medium",
        "last_reviewed": null,
        "sr_score": 0,
        "attempted": false
    },
    {
        "id": 246,
        "name": "Dota2 Senate",
        "url": "https://neetcode.io/problems/dota2-senate",
        "difficulty": "medium",
        "last_reviewed": null,
        "sr_score": 0,
        "attempted": false
    },
    {
        "id": 247,
        "name": "Candy",
        "url": "https://neetcode.io/problems/candy",
        "difficulty": "hard",
        "last_reviewed": null,
        "sr_score": 0,
        "attempted": false
    },
    {
        "id": 248,
        "name": "Meeting Rooms III",
        "url": "https://neetcode.io/problems/meeting-rooms-iii",
        "difficulty": "hard",
        "last_reviewed": null,
        "sr_score": 0,
        "attempted": false
    },
    {
        "id": 249,
        "name": "Excel Sheet Column Title",
        "url": "https://neetcode.io/problems/excel-sheet-column-title",
        "difficulty": "easy",
        "last_reviewed": null,
        "sr_score": 0,
        "attempted": false
    },
    {
        "id": 250,
        "name": "Greatest Common Divisor of Strings",
        "url": "https://neetcode.io/problems/greatest-common-divisor-of-strings",
        "difficulty": "easy",
        "last_reviewed": null,
        "sr_score": 0,
        "attempted": false
    },
    {
        "id": 251,
        "name": "Transpose Matrix",
        "url": "https://neetcode.io/problems/transpose-matrix",
        "difficulty": "easy",
        "last_reviewed": null,
        "sr_score": 0,
        "attempted": false
    },
    {
        "id": 252,
        "name": "Insert Greatest Common Divisors in Linked List",
        "url": "https://neetcode.io/problems/insert-greatest-common-divisors-in-linked-list",
        "difficulty": "medium",
        "last_reviewed": null,
        "sr_score": 0,
        "attempted": false
    },
    {
        "id": 253,
        "name": "Roman to Integer",
        "url": "https://neetcode.io/problems/roman-to-integer",
        "difficulty": "easy",
        "last_reviewed": null,
        "sr_score": 0,
        "attempted": false
    },
    {
        "id": 254,
        "name": "Add Binary",
        "url": "https://neetcode.io/problems/add-binary",
        "difficulty": "easy",
        "last_reviewed": null,
        "sr_score": 0,
        "attempted": false
    },
    {
        "id": 255,
        "name": "Bitwise AND of Numbers Range",
        "url": "https://neetcode.io/problems/bitwise-and-of-numbers-range",
        "difficulty": "medium",
        "last_reviewed": null,
        "sr_score": 0,
        "attempted": false
    },
    {
        "id": 256,
        "name": "Minimum Array End",
        "url": "https://neetcode.io/problems/minimum-array-end",
        "difficulty": "medium",
        "last_reviewed": null,
        "sr_score": 0,
        "attempted": false
    },
    {
        "id": 257,
        "name": "Find Critical and Pseudo Critical Edges in Minimum Spanning Tree",
        "url": "https://neetcode.io/problems/find-critical-and-pseudo-critical-edges-in-minimum-spanning-tree",
        "difficulty": "hard",
        "last_reviewed": null,
        "sr_score": 0,
        "attempted": false
    },
    {
        "id": 258,
        "name": "Build a Matrix With Conditions",
        "url": "https://neetcode.io/problems/build-a-matrix-with-conditions",
        "difficulty": "hard",
        "last_reviewed": null,
        "sr_score": 0,
        "attempted": false
    },
    {
        "id": 259,
        "name": "Minimum Height Trees",
        "url": "https://neetcode.io/problems/minimum-height-trees",
        "difficulty": "medium",
        "last_reviewed": null,
        "sr_score": 0,
        "attempted": false
    },
    {
        "id": 260,
        "name": "Design Circular Queue",
        "url": "https://neetcode.io/problems/design-circular-queue",
        "difficulty": "medium",
        "last_reviewed": null,
        "sr_score": 0,
        "attempted": false
    },
    {
        "id": 261,
        "name": "LFU Cache",
        "url": "https://neetcode.io/problems/lfu-cache",
        "difficulty": "hard",
        "last_reviewed": null,
        "sr_score": 0,
        "attempted": false
    },
    {
        "id": 262,
        "name": "Implement Stack Using Queues",
        "url": "https://neetcode.io/problems/implement-stack-using-queues",
        "difficulty": "easy",
        "last_reviewed": null,
        "sr_score": 0,
        "attempted": false
    },
    {
        "id": 263,
        "name": "Implement Queue using Stacks",
        "url": "https://neetcode.io/problems/implement-queue-using-stacks",
        "difficulty": "easy",
        "last_reviewed": null,
        "sr_score": 0,
        "attempted": false
    },
    {
        "id": 264,
        "name": "Online Stock Span",
        "url": "https://neetcode.io/problems/online-stock-span",
        "difficulty": "medium",
        "last_reviewed": null,
        "sr_score": 0,
        "attempted": false
    },
    {
        "id": 265,
        "name": "Maximum Frequency Stack",
        "url": "https://neetcode.io/problems/maximum-frequency-stack",
        "difficulty": "hard",
        "last_reviewed": null,
        "sr_score": 0,
        "attempted": false
    },
    {
        "id": 266,
        "name": "Design Hashset",
        "url": "https://neetcode.io/problems/design-hashset",
        "difficulty": "easy",
        "last_reviewed": null,
        "sr_score": 0,
        "attempted": false
    },
    {
        "id": 267,
        "name": "Design HashMap",
        "url": "https://neetcode.io/problems/design-hashmap",
        "difficulty": "easy",
        "last_reviewed": null,
        "sr_score": 0,
        "attempted": false
    },
    {
        "id": 268,
        "name": "Range Sum Query 2D Immutable",
        "url": "https://neetcode.io/problems/range-sum-query-2d-immutable",
        "difficulty": "medium",
        "last_reviewed": null,
        "sr_score": 0,
        "attempted": false
    },
    {
        "id": 269,
        "name": "Longest Continuous Subarray With Absolute Diff Less Than or Equal to Limit",
        "url": "https://neetcode.io/problems/longest-continuous-subarray-with-absolute-diff-less-than-or-equal-to-limit",
        "difficulty": "medium",
        "last_reviewed": null,
        "sr_score": 0,
        "attempted": false
    },
    {
        "id": 270,
        "name": "Rotating the Box",
        "url": "https://neetcode.io/problems/rotating-the-box",
        "difficulty": "medium",
        "last_reviewed": null,
        "sr_score": 0,
        "attempted": false
    },
    {
        "id": 271,
        "name": "Find Peak Element",
        "url": "https://neetcode.io/problems/find-peak-element",
        "difficulty": "medium",
        "last_reviewed": null,
        "sr_score": 0,
        "attempted": false
    },
    {
        "id": 272,
        "name": "Sum Root to Leaf Numbers",
        "url": "https://neetcode.io/problems/sum-root-to-leaf-numbers",
        "difficulty": "medium",
        "last_reviewed": null,
        "sr_score": 0,
        "attempted": false
    },
    {
        "id": 273,
        "name": "Range Sum of BST",
        "url": "https://neetcode.io/problems/range-sum-of-bst",
        "difficulty": "easy",
        "last_reviewed": null,
        "sr_score": 0,
        "attempted": false
    },
    {
        "id": 274,
        "name": "Shortest Path in Binary Matrix",
        "url": "https://neetcode.io/problems/shortest-path-in-binary-matrix",
        "difficulty": "medium",
        "last_reviewed": null,
        "sr_score": 0,
        "attempted": false
    },
    {
        "id": 275,
        "name": "Squares of a Sorted Array",
        "url": "https://neetcode.io/problems/squares-of-a-sorted-array",
        "difficulty": "easy",
        "last_reviewed": null,
        "sr_score": 0,
        "attempted": false
    },
    {
        "id": 276,
        "name": "Find First And Last Position of Element In Sorted Array",
        "url": "https://neetcode.io/problems/find-first-and-last-position-of-element-in-sorted-array",
        "difficulty": "medium",
        "last_reviewed": null,
        "sr_score": 0,
        "attempted": false
    },
    {
        "id": 277,
        "name": "Basic Calculator II",
        "url": "https://neetcode.io/problems/basic-calculator-ii",
        "difficulty": "medium",
        "last_reviewed": null,
        "sr_score": 0,
        "attempted": false
    },
    {
        "id": 278,
        "name": "Lowest Common Ancestor of a Binary Tree III",
        "url": "https://neetcode.io/problems/lowest-common-ancestor-of-a-binary-tree-iii",
        "difficulty": "medium",
        "last_reviewed": null,
        "sr_score": 0,
        "attempted": false
    },
    {
        "id": 279,
        "name": "Palindrome Number",
        "url": "https://neetcode.io/problems/palindrome-number",
        "difficulty": "easy",
        "last_reviewed": null,
        "sr_score": 0,
        "attempted": false
    },
    {
        "id": 280,
        "name": "Zigzag Conversion",
        "url": "https://neetcode.io/problems/zigzag-conversion",
        "difficulty": "medium",
        "last_reviewed": null,
        "sr_score": 0,
        "attempted": false
    },
    {
        "id": 281,
        "name": "Pascal's Triangle",
        "url": "https://neetcode.io/problems/pascals-triangle",
        "difficulty": "easy",
        "last_reviewed": null,
        "sr_score": 0,
        "attempted": false
    },
    {
        "id": 282,
        "name": "Move Zeroes",
        "url": "https://neetcode.io/problems/move-zeroes",
        "difficulty": "easy",
        "last_reviewed": null,
        "sr_score": 0,
        "attempted": false
    },
    {
        "id": 283,
        "name": "Next Permutation",
        "url": "https://neetcode.io/problems/next-permutation",
        "difficulty": "medium",
        "last_reviewed": null,
        "sr_score": 0,
        "attempted": false
    },
    {
        "id": 284,
        "name": "Russian Doll Envelopes",
        "url": "https://neetcode.io/problems/russian-doll-envelopes",
        "difficulty": "hard",
        "last_reviewed": null,
        "sr_score": 0,
        "attempted": false
    },
    {
        "id": 285,
        "name": "K-th Smallest in Lexicographical Order",
        "url": "https://neetcode.io/problems/k-th-smallest-in-lexicographical-order",
        "difficulty": "hard",
        "last_reviewed": null,
        "sr_score": 0,
        "attempted": false
    },
    {
        "id": 286,
        "name": "Number of Visible People in a Queue",
        "url": "https://neetcode.io/problems/number-of-visible-people-in-a-queue",
        "difficulty": "hard",
        "last_reviewed": null,
        "sr_score": 0,
        "attempted": false
    },
    {
        "id": 287,
        "name": "Distribute Candies Among Children II",
        "url": "https://neetcode.io/problems/distribute-candies-among-children-ii",
        "difficulty": "medium",
        "last_reviewed": null,
        "sr_score": 0,
        "attempted": false
    },
    {
        "id": 288,
        "name": "Concatenated Words",
        "url": "https://neetcode.io/problems/concatenated-words",
        "difficulty": "hard",
        "last_reviewed": null,
        "sr_score": 0,
        "attempted": false
    },
    {
        "id": 289,
        "name": "Integer to Roman",
        "url": "https://neetcode.io/problems/integer-to-roman",
        "difficulty": "medium",
        "last_reviewed": null,
        "sr_score": 0,
        "attempted": false
    },
    {
        "id": 290,
        "name": "Maximum Frequency After Subarray Operation",
        "url": "https://neetcode.io/problems/maximum-frequency-after-subarray-operation",
        "difficulty": "medium",
        "last_reviewed": null,
        "sr_score": 0,
        "attempted": false
    },
    {
        "id": 291,
        "name": "Maximize Y-Sum by Picking a Triplet of Distinct X-Values",
        "url": "https://neetcode.io/problems/maximize-ysum-by-picking-a-triplet-of-distinct-xvalues",
        "difficulty": "medium",
        "last_reviewed": null,
        "sr_score": 0,
        "attempted": false
    },
    {
        "id": 292,
        "name": "Flood Fill",
        "url": "https://neetcode.io/problems/flood-fill",
        "difficulty": "easy",
        "last_reviewed": null,
        "sr_score": 0,
        "attempted": false
    },
    {
        "id": 293,
        "name": "Lowest Common Ancestor of a Binary Tree",
        "url": "https://neetcode.io/problems/lowest-common-ancestor-of-a-binary-tree",
        "difficulty": "medium",
        "last_reviewed": null,
        "sr_score": 0,
        "attempted": false
    },
    {
        "id": 294,
        "name": "Max Consecutive Ones",
        "url": "https://neetcode.io/problems/max-consecutive-ones",
        "difficulty": "easy",
        "last_reviewed": null,
        "sr_score": 0,
        "attempted": false
    },
    {
        "id": 295,
        "name": "Kth Smallest Product of Two Sorted Arrays",
        "url": "https://neetcode.io/problems/kth-smallest-product-of-two-sorted-arrays",
        "difficulty": "hard",
        "last_reviewed": null,
        "sr_score": 0,
        "attempted": false
    },
    {
        "id": 296,
        "name": "Frequency of The Most Frequent Element",
        "url": "https://neetcode.io/problems/frequency-of-the-most-frequent-element",
        "difficulty": "medium",
        "last_reviewed": null,
        "sr_score": 0,
        "attempted": false
    },
    {
        "id": 297,
        "name": "Maximum Difference Between Even and Odd Frequency I",
        "url": "https://neetcode.io/problems/maximum-difference-between-even-and-odd-frequency-i",
        "difficulty": "easy",
        "last_reviewed": null,
        "sr_score": 0,
        "attempted": false
    },
    {
        "id": 298,
        "name": "Intersection of Two Linked Lists",
        "url": "https://neetcode.io/problems/intersection-of-two-linked-lists",
        "difficulty": "easy",
        "last_reviewed": null,
        "sr_score": 0,
        "attempted": false
    },
    {
        "id": 299,
        "name": "Find The Index of The First Occurrence in a String",
        "url": "https://neetcode.io/problems/find-the-index-of-the-first-occurrence-in-a-string",
        "difficulty": "easy",
        "last_reviewed": null,
        "sr_score": 0,
        "attempted": false
    },
    {
        "id": 300,
        "name": "Recover Binary Search Tree",
        "url": "https://neetcode.io/problems/recover-binary-search-tree",
        "difficulty": "medium",
        "last_reviewed": null,
        "sr_score": 0,
        "attempted": false
    }
]